EFX/__init__.py
EFX/main.py
encfilex-3.1.dist-info/licenses/LICENSE
encfilex-3.1.dist-info/METADATA
encfilex-3.1.dist-info/WHEEL
encfilex-3.1.dist-info/entry_points.txt
encfilex-3.1.dist-info/top_level.txt
encfilex-3.1.dist-info/RECORD
