Metadata-Version: 2.4
Name: encfilex
Version: 3.1
Summary: EncFilex v3 - layered file encryption (Base64 -> AES-256-GCM -> XChaCha20-Poly1305)
Author-email: AkuzzDev <akuzz.developer@gmail.com>
License: MIT
Requires-Python: >=3.9
License-File: LICENSE
Requires-Dist: argon2-cffi
Requires-Dist: cryptography
Requires-Dist: PyNaCl
Dynamic: license-file
